{
  "categories": [
    "curly",
    "display",
    "elegant",
    "initials"
  ],
  "classifications": [
    "display"
  ],
  "creator": "Paul Lloyd",
  "variant": "regular",
  "source": "fontsquirrel",
  "family": "Dutch Initials",
  "font_family_name": "Dutch Initials",
  "full_font_name": "Dutch Initials Normal",
  "font_subfamily_name": "normal",
  "postscript_name": "DutchInitials",
  "version_string": "001.003",
  "last_modified": 1253602800000,
  "size": 52134,
  "weight_class": 400,
  "rank": 699
}