{
  "categories": [
    "Techno",
    "Various"
  ],
  "variant": "700",
  "source": "dafont",
  "family": "Avengeance Heroic Avenger",
  "font_family_name": "Avengeance Heroic Avenger",
  "full_font_name": "Avengeance Heroic Avenger Bold",
  "font_subfamily_name": "Bold",
  "postscript_name": "AvengeanceHeroicAvengerBold",
  "trademark": "Avengeance Heroic Avenger Bold is a trademark of The Fontry.",
  "manufacturer": "The Fontry",
  "version_string": "",
  "last_modified": 0,
  "size": 100980,
  "weight_class": 700,
  "rank": 113
}