{
  "categories": [
    "Basic",
    "Serif"
  ],
  "variant": "600",
  "source": "dafont",
  "family": "Linux Libertine",
  "font_family_name": "Linux Libertine",
  "full_font_name": "Linux Libertine Semibold",
  "font_subfamily_name": "Semibold",
  "postscript_name": "LinLibertineZ",
  "manufacturer": "Philipp H. Poll",
  "designer": "Philipp H. Poll",
  "designer_url": "http://linuxlibertine.sf.net",
  "vendor_url": "http://linuxlibertine.sf.net",
  "license_desciption": "GPL- General Public License AND OFL-Open Font License",
  "license_url": "http://www.fsf.org/licenses/gpl.html AND http://scripts.sil.org/OFL",
  "version_string": "Version 5.1.1 ",
  "last_modified": 0,
  "size": 771388,
  "weight_class": 600,
  "rank": 719
}