{
  "categories": [
    "Script",
    "Various"
  ],
  "variant": "500",
  "source": "dafont",
  "family": "MRF On the Edge of Crazy",
  "font_family_name": "MRF On the Edge of Crazy",
  "full_font_name": "MRF_ On the Edge of Crazy",
  "font_subfamily_name": "Medium",
  "postscript_name": "MRFOntheEdgeofCrazy-Medium",
  "designer": "Sabrina Schleiger",
  "designer_url": "www.monkeyroodlesfonts.com",
  "license_url": "www.monkeyroodlesfonts.com",
  "version_string": "Version 001.000",
  "last_modified": 0,
  "size": 27544,
  "weight_class": 500,
  "rank": 323
}