{
  "categories": [
    "oblique"
  ],
  "classifications": [
    "sans-serif"
  ],
  "creator": "Andriy Shevchenko",
  "varient": "regular",
  "source": "fontsquirrel",
  "family": "Arsenal",
  "font_family_name": "Arsenal",
  "full_font_name": "Arsenal-Regular",
  "font_subfamily_name": "Regular",
  "postscript_name": "Arsenal-Regular",
  "trademark": "Arsenal is a trademark of Stairsfor.",
  "manufacturer": "Stairsfor.com",
  "designer": "Andrij Shevchenko",
  "designer_url": "http://andrij.com.ua/",
  "vendor_url": "http://stairsfor.com/",
  "license_url": "http://scripts.sil.org/OFL",
  "version_string": "Version 1.000",
  "last_modified": 1363849200000,
  "size": 124048,
  "weight_class": 400,
  "rank": 215
}