{
  "categories": [
    "paragraph",
    "serif",
    "transitional"
  ],
  "classifications": [
    "serif"
  ],
  "creator": "Google Android",
  "varient": "italic",
  "source": "fontsquirrel",
  "family": "Droid Serif",
  "font_family_name": "Droid Serif",
  "full_font_name": "Droid Serif Italic",
  "font_subfamily_name": "Italic",
  "postscript_name": "DroidSerif-Italic",
  "trademark": "Droid is a trademark of Google and may be registered in certain jurisdictions.",
  "manufacturer": "Ascender Corporation",
  "designer_url": "http://www.ascendercorp.com/typedesigners.html",
  "vendor_url": "http://www.ascendercorp.com/",
  "license_desciption": "Licensed under the Apache License, Version 2.0",
  "license_url": "http://www.apache.org/licenses/LICENSE-2.0",
  "version_string": "Version 1.00 build 113",
  "last_modified": 1230883200000,
  "size": 177560,
  "weight_class": 400,
  "rank": 52
}