{
  "categories": [
    "Gothic",
    "Medieval"
  ],
  "varient": "regular",
  "source": "dafont",
  "family": "Holland Morlaeu",
  "font_family_name": "HollandMorlaeu",
  "full_font_name": "HollandMorlaeu Regular",
  "font_subfamily_name": "Regular",
  "postscript_name": "HollandMorlaeu-Regular",
  "trademark": "HollandMorlaeu Regular is a trademark of Paulo W.",
  "manufacturer": "Paulo W",
  "version_string": "Version 1.000",
  "last_modified": 0,
  "size": 21372,
  "weight_class": 400,
  "rank": 338
}