{
  "subsets": [
    "latin",
    "latin-ext"
  ],
  "categories": [
    "display"
  ],
  "classifications": [
    "display"
  ],
  "creator": "Fontstage",
  "variant": "900",
  "source": "googlefonts",
  "family": "Passion One",
  "font_family_name": "Passion One",
  "full_font_name": "Passion One Black",
  "font_subfamily_name": "Black",
  "postscript_name": "PassionOne-Black",
  "trademark": "Passion is a trademark of Fontstage.",
  "manufacturer": "Fontstage",
  "designer": "Alejandro Lo Celso",
  "designer_url": "www.fontstage.com",
  "vendor_url": "www.fontstage.com",
  "license_desciption": "This Font Software is licensed under the SIL Open Font License, Version 1.1. This license is available with a FAQ at: http://scripts.sil.org/OFL",
  "license_url": "http://scripts.sil.org/OFL",
  "version_string": "Version 1.001",
  "description": "Passion One is a set of 3 display fonts aimed to composing titles in big sizes. Its counterforms decrease as the passion increases! Please use them only for your most passionate thoughts and ideas.",
  "last_modified": 1456214400000,
  "size": 24320,
  "weight_class": 900,
  "rank": 26
}