{
  "categories": [
    "bouncy",
    "casual",
    "childish",
    "handwritten",
    "humorous",
    "serif",
    "serif",
    "slab",
    "whimsical"
  ],
  "classifications": [
    "handdrawn"
  ],
  "creator": "pizzadude.dk",
  "varient": "regular",
  "source": "fontsquirrel",
  "family": "Idolwild",
  "font_family_name": "Idolwild",
  "full_font_name": "Idolwild",
  "font_subfamily_name": "Regular",
  "postscript_name": "Idolwild",
  "trademark": "",
  "version_string": "1, 2005",
  "last_modified": 1230710400000,
  "size": 56080,
  "weight_class": 400,
  "rank": 187
}