{
  "categories": [
    "Script",
    "Calligraphy"
  ],
  "variant": "regular",
  "source": "dafont",
  "family": "King City",
  "font_family_name": "King City Free Font",
  "full_font_name": "KingCityFreeFont",
  "font_subfamily_name": "Calligraphy",
  "postscript_name": "KingCityFreeFont",
  "trademark": "Fey Design (Ferry Hadriyan)",
  "manufacturer": "Fey Design (Ferry Hadriyan)",
  "version_string": "Version 1.000;PS 001.001;hotconv 1.0.56",
  "last_modified": 0,
  "size": 35048,
  "weight_class": 400,
  "rank": 5
}